envoy/github/abstract/__init__.py
envoy/github/abstract/assets.py
envoy/github/abstract/command.py
envoy/github/abstract/exceptions.py
envoy/github/abstract/manager.py
envoy/github/abstract/py.typed
envoy/github/abstract/release.py
envoy/github/abstract/runner.py
envoy.github.abstract-0.0.22.dist-info/METADATA
envoy.github.abstract-0.0.22.dist-info/WHEEL
envoy.github.abstract-0.0.22.dist-info/namespace_packages.txt
envoy.github.abstract-0.0.22.dist-info/top_level.txt
envoy.github.abstract-0.0.22.dist-info/RECORD
