Metadata-Version: 2.1
Name: envoy.github.abstract
Version: 0.0.22
Summary: "Abstract interfaces for the Github release tool used in Envoy proxy's CI"
Home-page: https://github.com/envoyproxy/pytooling/tree/main/envoy.github.abstract
Author: Ryan Northey
Author-email: ryan@synca.io
Maintainer: Ryan Northey
Maintainer-email: ryan@synca.io
License: Apache Software License 2.0
Platform: UNKNOWN
Requires-Dist: abstracts (>=0.0.12)
Requires-Dist: aio.core (>=0.3.0)
Requires-Dist: aio.run.runner (>=0.2.1)
Requires-Dist: aiohttp
Requires-Dist: gidgethub
Requires-Dist: packaging
Requires-Dist: verboselogs
